pyexcel_yuri/__init__.py
pyexcel_yuri/csvr.py
pyexcel_yuri/csvw.py
pyexcel_yuri/xlsxr.py
pyexcel_yuri/xlsxw.py
pyexcel_yuri-0.0.3.dist-info/METADATA
pyexcel_yuri-0.0.3.dist-info/RECORD
pyexcel_yuri-0.0.3.dist-info/WHEEL
pyexcel_yuri-0.0.3.dist-info/top_level.txt
