Metadata-Version: 2.1
Name: pyexcel-yuri
Version: 0.0.3
Summary: A wrapper library to read, manipulate and write data format
Home-page: https://github.com/Yuri-x/pyexcel-yuri
Author: Yuri
Author-email: yuri@yuri-x.com
License: New BSD
Download-URL: https://github.com/Yuri-x/pyexcel-yuri/archive/0.0.3.tar.gz
Requires-Dist: openpyxl (>=2.5.0)
Requires-Dist: pyexcel-io (>=0.5.3)
Requires-Dist: Xlsxwriter
Requires-Dist: pandas (>=0.23.4)
